CHANGES.rst
MANIFEST.in
Makefile
README.rst
VERSION
setup.py
msisdn_cli/__init__.py
msisdn_cli.egg-info/PKG-INFO
msisdn_cli.egg-info/SOURCES.txt
msisdn_cli.egg-info/dependency_links.txt
msisdn_cli.egg-info/entry_points.txt
msisdn_cli.egg-info/requires.txt
msisdn_cli.egg-info/top_level.txt
msisdn_cli.egg-info/zip-safe