Metadata-Version: 1.1
Name: msisdn-cli
Version: 1.0
Summary: MSISDN Gateway CLI tool.
Home-page: https://github.com/mozilla-services/msisdn-cli
Author: Mozilla (https://mozilla.org/)
Author-email: UNKNOWN
License: BSD
Keywords: msisdn sms browserid
Platform: UNKNOWN
Classifier: Development Status :: 4 - Beta
Classifier: License :: OSI Approved :: Mozilla Public License 1.0 (MPL)
Classifier: Programming Language :: Python :: 3
Classifier: Programming Language :: Python :: 3.4
Classifier: Programming Language :: Python :: 2.7
Classifier: Programming Language :: Python :: 2.6
Classifier: Topic :: Internet :: WWW/HTTP
